{
  "teamId": "03",
  "lang": "ZH",
  "region": "美國",
  "project": "創新脂肪幹細胞生物製程 客製化生成骨骼移植物",
  "company": "EpiBone",
  "contact": { "name": "Nina Tandon", "occupation": "CEO", "avatarUrl": "https://expo.taiwan-healthcare.org/data/cht/20241104/202411044qpmk8.jpeg" },
  "logoUrl": "https://expo.taiwan-healthcare.org/data/cht/20241104/20241104npf0v7.png",
  "mainInvester": "Kendall Capital Partners, NJ Tech Council Ventures",
  "established": "2013",
  "fundingAmount": "5,000萬美元",
  "annualRevenue": "N/A",
  "currentFundingRound": "Pre-B bridge",
  "currentFundingAmount": "200萬美元",
  "postMoneyValuation": "1億美元",
  "highlights": ["全球首家也是唯一經美國FDA核准執行臨床試驗的幹細胞骨和軟骨產品，在 2021-2022 期間於 6 名患者身上已取得初步成功。", "目前正擴展至海灣GCC地區，目標為取得中東和亞洲地區的上市許可。"],
  "coreTech": "利用人工智慧、機器人技術和生物3D列印製造，由成人脂肪和骨髓幹細胞改造重塑精確的骨骼和軟骨移植物。",
  "coreTechKeywords": ["組織工程", "再生醫學", "3D生物列印"],
  "targetMarket": "全球骨科、顱顏和重建手術市場，及中東/北非和亞洲地區的醫療旅遊市場。",
  "coreProducts": [
    { "name": "PANTHEON™\n", "type": "drug", "progress": "0.75", "countries": "歐盟CE、新加坡\n" },
    { "name": "QAi AI Prostate Dx", "type": "drug", "progress": "0.75", "countries": "新加坡" },
    { "name": "Bone", "type": "device", "progress": "0.7", "countries": "" },
    { "name": "Cartilage", "type": "device", "progress": "0.5", "countries": "" }
  ],
  "milestones": ["全球骨科、顱顏和重建手術市場，及中東/北非和亞洲地區的醫療旅遊市場。", "阿聯和泰國臨床試驗的法規核准與執行"]
}
